scAllele/__init__.py
scAllele/gqv_bam_utils.py
scAllele/gqv_dbg_utils.py
scAllele/gqv_glm.py
scAllele/gqv_mutual_information.py
scAllele/gqv_software_management.py
scAllele/gqv_utils.py
scAllele/gqv_vartool.py
scAllele/scAllele.py
scAllele/glm/GM12878_smartseq2.all.feature_matrix.tab.DELETION.glm.pickle
scAllele/glm/GM12878_smartseq2.all.feature_matrix.tab.INSERTION.glm.pickle
scAllele/glm/GM12878_smartseq2.all.feature_matrix.tab.SNP.glm.pickle
scAllele/glm/GM12878_smartseq2.all.feature_matrix.tab.SNV.glm.pickle
scAllele/glm/__init__.py
scAllele-0.0.9.4.dist-info/LICENSE
scAllele-0.0.9.4.dist-info/METADATA
scAllele-0.0.9.4.dist-info/WHEEL
scAllele-0.0.9.4.dist-info/entry_points.txt
scAllele-0.0.9.4.dist-info/top_level.txt
scAllele-0.0.9.4.dist-info/RECORD
