Metadata-Version: 2.1
Name: scAllele
Version: 0.0.9.4
Summary: A versatile tool for the detection and analysis of nucleotide variants in scRNA-seq
Home-page: https://github.com/gxiaolab/scAllele
Author: Giovanni Quinones Valdez
Author-email: giovas@ucla.edu
Project-URL: Bug Tracker, https://github.com/gxiaolab/scAllele/issues
Classifier: Programming Language :: Python :: 3
Classifier: License :: OSI Approved :: MIT License
Classifier: Operating System :: OS Independent
Requires-Python: >=3.8
License-File: LICENSE
Requires-Dist: biopython
Requires-Dist: glob2
Requires-Dist: HTSeq
Requires-Dist: multiprocess
Requires-Dist: networkx >=2.4
Requires-Dist: numpy
Requires-Dist: pandas >=1.3
Requires-Dist: pickleshare
Requires-Dist: psutil
Requires-Dist: pyfaidx >=0.5.9.5
Requires-Dist: pysam >=0.9.1
Requires-Dist: vcfpy
Requires-Dist: scikit-learn >=0.23.1
Requires-Dist: scipy
Requires-Dist: statsmodels >=0.11.1
